free_mcp_excel/__init__.py
free_mcp_excel/__main__.py
free_mcp_excel/calculator.py
free_mcp_excel/chart_handler.py
free_mcp_excel/parser.py
free_mcp_excel/server.py
free_mcp_excel/utils.py
free_mcp_excel/writer.py
free_mcp_excel-0.1.3.dist-info/licenses/LICENSE
free_mcp_excel-0.1.3.dist-info/METADATA
free_mcp_excel-0.1.3.dist-info/WHEEL
free_mcp_excel-0.1.3.dist-info/entry_points.txt
free_mcp_excel-0.1.3.dist-info/top_level.txt
free_mcp_excel-0.1.3.dist-info/RECORD
