Metadata-Version: 2.4
Name: free-mcp-excel
Version: 0.1.3
Summary: 本地Excel MCP服务，提供Excel文件解析能力
Author-email: fanzhiyu <fanzhiyu7410@163.com>
License: MIT
Project-URL: Homepage, https://gitee.com/fanzhiyu/free-mcp-excel
Project-URL: Documentation, https://gitee.com/fanzhiyu/free-mcp-excel#readme
Project-URL: Repository, https://gitee.com/fanzhiyu/free-mcp-excel
Project-URL: Issues, https://gitee.com/fanzhiyu/free-mcp-excel/issues
Keywords: mcp,excel,model-context-protocol,ai
Classifier: Development Status :: 3 - Alpha
Classifier: Intended Audience :: Developers
Classifier: License :: OSI Approved :: MIT License
Classifier: Programming Language :: Python :: 3
Classifier: Programming Language :: Python :: 3.8
Classifier: Programming Language :: Python :: 3.9
Classifier: Programming Language :: Python :: 3.10
Classifier: Programming Language :: Python :: 3.11
Classifier: Programming Language :: Python :: 3.12
Requires-Python: >=3.8
License-File: LICENSE
Requires-Dist: mcp>=0.9.0
Requires-Dist: openpyxl>=3.0.0
Requires-Dist: pandas>=1.5.0
Requires-Dist: xlrd>=2.0.0
Requires-Dist: xlwt>=1.3.0
Requires-Dist: pycel>=1.0b0
Provides-Extra: dev
Requires-Dist: pytest>=7.0.0; extra == "dev"
Requires-Dist: pytest-asyncio>=0.21.0; extra == "dev"
Requires-Dist: pytest-cov>=4.0.0; extra == "dev"
Requires-Dist: pytest-mock>=3.10.0; extra == "dev"
Requires-Dist: pytest-benchmark>=4.0.0; extra == "dev"
Requires-Dist: black>=23.0.0; extra == "dev"
Requires-Dist: flake8>=6.0.0; extra == "dev"
Dynamic: license-file
